lilliepy_utils/__init__.py
lilliepy_utils/main.py
lilliepy_utils-0.1.0.dist-info/METADATA
lilliepy_utils-0.1.0.dist-info/WHEEL
lilliepy_utils-0.1.0.dist-info/top_level.txt
lilliepy_utils-0.1.0.dist-info/RECORD
